{
  "type": "FeatureCollection",
  "features": [
    {
      "type": "Feature",
      "properties": {
        "shape": "CircleMarker",
        "name": "Unnamed Layer",
        "category": "default"
      },
      "geometry": {
        "type": "Point",
        "coordinates": [
          16.643772,
          49.206383
        ]
      },
      "id": "74615405-76e9-47f4-8b46-3cd1d6973d9a"
    },
    {
      "type": "Feature",
      "properties": {
        "shape": "Polygon",
        "name": "Unnamed Layer",
        "category": "default"
      },
      "geometry": {
        "type": "Polygon",
        "coordinates": [
          [
            [
              16.570988,
              49.20885
            ],
            [
              16.578026,
              49.193147
            ],
            [
              16.553822,
              49.176878
            ],
            [
              16.598282,
              49.167451
            ],
            [
              16.619396,
              49.185967
            ],
            [
              16.610985,
              49.204813
            ],
            [
              16.570988,
              49.20885
            ]
          ]
        ]
      },
      "id": "e60cbb7f-2986-4f59-9120-ab1612826ccf"
    }
  ]
}